everdrop_aws_cdk_constructs/__init__.py
everdrop_aws_cdk_constructs/py.typed
everdrop_aws_cdk_constructs/_jsii/__init__.py
everdrop_aws_cdk_constructs/_jsii/everdrop-aws-cdk-constructs@0.0.123.jsii.tgz
everdrop_aws_cdk_constructs-0.0.123.dist-info/LICENSE
everdrop_aws_cdk_constructs-0.0.123.dist-info/METADATA
everdrop_aws_cdk_constructs-0.0.123.dist-info/WHEEL
everdrop_aws_cdk_constructs-0.0.123.dist-info/top_level.txt
everdrop_aws_cdk_constructs-0.0.123.dist-info/RECORD
